maltsev_repeater/__init__.py
maltsev_repeater/repeater.py
maltsev_repeater/repeater_result.py
maltsev_repeater-1.0.1.dist-info/LICENSE
maltsev_repeater-1.0.1.dist-info/METADATA
maltsev_repeater-1.0.1.dist-info/WHEEL
maltsev_repeater-1.0.1.dist-info/RECORD
