Metadata-Version: 2.1
Name: maltsev-repeater
Version: 1.0.1
Summary: 
Home-page: https://github.com/victormaltsev/Maltsev.Repeater
License: MIT
Author: Victor Maltsev
Author-email: git@victormaltsev.com
Classifier: License :: OSI Approved :: MIT License
Classifier: Programming Language :: Python :: 2
Classifier: Programming Language :: Python :: 2.7
Classifier: Programming Language :: Python :: 3
Classifier: Programming Language :: Python :: 3.4
Classifier: Programming Language :: Python :: 3.5
Classifier: Programming Language :: Python :: 3.6
Classifier: Programming Language :: Python :: 3.7
Classifier: Programming Language :: Python :: 3.8
Classifier: Programming Language :: Python :: 3.9
Classifier: Programming Language :: Python :: 3.10
Classifier: Programming Language :: Python :: 3.11
Project-URL: Repository, https://github.com/victormaltsev/Maltsev.Repeater
